pydictobject
