Metadata-Version: 2.1
Name: pydictobject
Version: 1.3
Summary: pydictobject - a dictionary that is accessible like an object
Home-page: https://github.com/pdrharris/pydictobject
Author: Peter Harris
Author-email: pdrharris@gmail.com
License: UNKNOWN
Download-URL: https://github.com/pdrharris/pydictobject/archive/1.03.tar.gz
Platform: UNKNOWN
Classifier: Programming Language :: Python :: 3
Classifier: License :: OSI Approved :: MIT License
Classifier: Operating System :: OS Independent
